<settings>
    <global>
        <X>0</X>
        <Y>0</Y>
        <Zoom>100</Zoom>
        <Opacity>75</Opacity>
        <ShowPC>true</ShowPC>
        <ShowNPC>true</ShowNPC>
        <ShowMob>true</ShowMob>
        <ShowMarker>true</ShowMarker>
        <ShowTargetLine>true</ShowTargetLine>
        <Ranges />
        <Scale>1</Scale>
        <ColorPC>#FF006FB8</ColorPC>
        <ColorNPC>#FF269D49</ColorNPC>
        <ColorMob>#FFED1A20</ColorMob>
        <ColorMarker>#FFB646AD</ColorMarker>
        <ZoomDefault>-10</ZoomDefault>
    </global>
    <Dreameyes>
        <X>1528</X>
        <Y>845</Y>
        <Zoom>100</Zoom>
    </Dreameyes>
    <Agentplatinum>
        <X>1678</X>
        <Y>701</Y>
    </Agentplatinum>
    <Tkilla>
        <X>1592</X>
        <Y>705</Y>
        <Zoom>30</Zoom>
    </Tkilla>
    <Ollyb>
        <X>1672</X>
        <Y>720</Y>
    </Ollyb>
    <Bolly>
        <X>1664</X>
        <Y>783</Y>
    </Bolly>
    <Goddzila>
        <X>1615</X>
        <Y>731</Y>
    </Goddzila>
    <Trognon>
        <X>1515</X>
        <Y>836</Y>
        <Zoom>20</Zoom>
    </Trognon>
    <Ronieh>
        <X>1664</X>
        <Y>709</Y>
    </Ronieh>
    <Roniee>
        <X>1689</X>
        <Y>617</Y>
    </Roniee>
    <Jardin>
        <X>1696</X>
        <Y>720</Y>
    </Jardin>
    <Poiscaille>
        <X>1546</X>
        <Y>705</Y>
    </Poiscaille>
    <Roniem>
        <X>1257</X>
        <Y>578</Y>
    </Roniem>
    <Viiiiii>
        <X>1687</X>
        <Y>414</Y>
    </Viiiiii>
    <Ollya>
        <X>1685</X>
        <Y>398</Y>
    </Ollya>
    <Bollya>
        <X>1657</X>
        <Y>458</Y>
    </Bollya>
    <Ollyyyy>
        <X>1677</X>
        <Y>388</Y>
    </Ollyyyy>
    <Roniex>
        <X>1632</X>
        <Y>705</Y>
    </Roniex>
    <Roniew>
        <X>1664</X>
        <Y>730</Y>
        <Zoom>40</Zoom>
    </Roniew>
    <Testee>
        <X>1635</X>
        <Y>676</Y>
    </Testee>
    <Agentwhit>
        <X>1620</X>
        <Y>612</Y>
    </Agentwhit>
    <Pikkachuu>
        <X>1608</X>
        <Y>604</Y>
    </Pikkachuu>
    <Gilman>
        <X>1647</X>
        <Y>623</Y>
    </Gilman>
    <Monkky>
        <X>1582</X>
        <Y>451</Y>
    </Monkky>
    <Mangeaille>
        <X>1622</X>
        <Y>463</Y>
    </Mangeaille>
    <Bouffetout>
        <X>1643</X>
        <Y>467</Y>
    </Bouffetout>
    <Roniev>
        <X>1629</X>
        <Y>446</Y>
    </Roniev>
    <Roniet>
        <X>1634</X>
        <Y>492</Y>
    </Roniet>
    <Roniek>
        <X>1655</X>
        <Y>563</Y>
    </Roniek>
    <Dreamon>
        <X>1659</X>
        <Y>687</Y>
    </Dreamon>
    <Leitsu>
        <X>1521</X>
        <Y>819</Y>
    </Leitsu>
    <Nareko>
        <X>1531</X>
        <Y>837</Y>
    </Nareko>
    <Zolooooo>
        <X>1541</X>
        <Y>663</Y>
    </Zolooooo>
    <Bolyo>
        <X>1538</X>
        <Y>620</Y>
    </Bolyo>
</settings>
